quandoo/Agent.py
quandoo/Customer.py
quandoo/Error.py
quandoo/Merchant.py
quandoo/QuandooModel.py
quandoo/Reservation.py
quandoo/ReservationEnquiry.py
quandoo/__init__.py
quandoo/config.py
Quandoo-1.3.7.dist-info/LICENSE.txt
Quandoo-1.3.7.dist-info/METADATA
Quandoo-1.3.7.dist-info/WHEEL
Quandoo-1.3.7.dist-info/top_level.txt
Quandoo-1.3.7.dist-info/RECORD
