Metadata-Version: 2.1
Name: Quandoo
Version: 1.3.7
Summary: A Python library to access the Quandoo API (v1). Base functionality is covered and more peripheral features are being covered in due course.
Home-page: https://github.com/fraser-langton/Quandoo
Author: Fraser Langton
Author-email: fraserbasil@gmail.com
License: UNKNOWN
Keywords: quandoo api
Platform: UNKNOWN
Classifier: Development Status :: 3 - Alpha
Classifier: Intended Audience :: Developers
Classifier: License :: OSI Approved :: MIT License
Classifier: Programming Language :: Python :: 3
Classifier: Programming Language :: Python :: 3.4
Classifier: Programming Language :: Python :: 3.5
Classifier: Programming Language :: Python :: 3.6
Classifier: Programming Language :: Python :: 3.7
Classifier: Programming Language :: Python :: 3.8
Requires-Python: >=2.7, !=3.0.*, !=3.1.*, !=3.2.*, !=3.3.*, <4
Requires-Dist: requests
Requires-Dist: tzlocal
Requires-Dist: python-dotenv
